<?xml version="1.0" encoding="utf-8" ?>
<Defs>
  <ResearchProjectDef>
    <defName>Research_150mmSIG33</defName>
    <label>15cm sIG 33</label>
      <description>Allows you to build 15 cm sIG 33</description> 
    <baseCost>700</baseCost>
    <techLevel>Industrial</techLevel>
    <prerequisites>
      <li>Howitzers</li>
    </prerequisites>
    <researchViewX>2</researchViewX>
    <researchViewY>4.5</researchViewY>
    <tab>AMC_General</tab>
  </ResearchProjectDef>
  <ResearchProjectDef>
    <defName>Research_233mmBLMK1</defName>
    <label>9.2in BL Howitzer Mk.1</label>
      <description>Allows you to build 9.2in BL Howitzer Mk.1</description> 
    <baseCost>1200</baseCost>
    <techLevel>Industrial</techLevel>
    <prerequisites>
      <li>Research_150mmSIG33</li>
    </prerequisites>
    <researchViewX>3</researchViewX>
    <researchViewY>4.5</researchViewY>
    <tab>AMC_General</tab>
  </ResearchProjectDef>
  <ResearchProjectDef>
    <defName>Research_600mmKarlGerat</defName>
    <label>Karl-Gerät 040</label>
      <description>Allows you to build Karl-Gerät 040</description> 
    <baseCost>2500</baseCost>
    <techLevel>Industrial</techLevel>
    <prerequisites>
      <li>Research_233mmBLMK1</li>
    </prerequisites>
    <researchViewX>4</researchViewX>
    <researchViewY>4.5</researchViewY>
    <tab>AMC_General</tab>
  </ResearchProjectDef>

  <ResearchProjectDef>
    <defName>Research_122mmGvozdika</defName>
    <label>2S1 Gvozdika</label>
      <description>Allows you to build 2S1 Gvozdika Howitzer Turret</description> 
    <baseCost>700</baseCost>
    <techLevel>Industrial</techLevel>
    <prerequisites>
      <li>Howitzers</li>
    </prerequisites>
    <researchViewX>2</researchViewX>
    <researchViewY>5.5</researchViewY>
    <tab>AMC_General</tab>
  </ResearchProjectDef>
  <ResearchProjectDef>
    <defName>Research_152mmAkatsiya</defName>
    <label>2S3 Akatsiya</label>
      <description>Allows you to build 2S3 Akatsiya Howitzer Turret</description> 
    <baseCost>1000</baseCost>
    <techLevel>Industrial</techLevel>
    <prerequisites>
      <li>Research_122mmGvozdika</li>
    </prerequisites>
    <researchViewX>3</researchViewX>
    <researchViewY>5.5</researchViewY>
    <tab>AMC_General</tab>
  </ResearchProjectDef>
  <ResearchProjectDef>
    <defName>Research_152mmMsta</defName>
    <label>2S19 Research_152mmMsta</label>
      <description>Allows you to build 2S19 Msta Howitzer Turret</description> 
    <baseCost>1500</baseCost>
    <techLevel>Industrial</techLevel>
    <prerequisites>
      <li>Research_152mmAkatsiya</li>
    </prerequisites>
    <researchViewX>4</researchViewX>
    <researchViewY>5.5</researchViewY>
    <tab>AMC_General</tab>
  </ResearchProjectDef>
  <ResearchProjectDef>
    <defName>Research_155mmGCT</defName>
    <label>155mm GCT AUF1</label>
      <description>Allows you to build 155mm GCT AUF1 Howitzer Turret</description> 
    <baseCost>2000</baseCost>
    <techLevel>Industrial</techLevel>
    <prerequisites>
      <li>Research_152mmMsta</li>
      <li>Fabrication</li>
    </prerequisites>
    <researchViewX>5</researchViewX>
    <researchViewY>5.5</researchViewY>
    <tab>AMC_General</tab>
  </ResearchProjectDef>
</Defs>